psycopg2/__init__.py
psycopg2/_ipaddress.py
psycopg2/_json.py
psycopg2/_range.py
psycopg2/errorcodes.py
psycopg2/extensions.py
psycopg2/extras.py
psycopg2/pool.py
psycopg2/psycopg1.py
psycopg2/sql.py
psycopg2/tz.py
awslambda_psycopg2-1.0.2.dist-info/METADATA
awslambda_psycopg2-1.0.2.dist-info/WHEEL
awslambda_psycopg2-1.0.2.dist-info/top_level.txt
awslambda_psycopg2-1.0.2.dist-info/RECORD
