Metadata-Version: 2.1
Name: awslambda-psycopg2
Version: 1.0.2
Summary: A aws psycopg2 package from psycopg2.
Home-page: https://github.com/jkehler/awslambda-psycopg2
Author: Yuvaraja
Author-email: yuvaraja.gna@gmail.com
License: UNKNOWN
Platform: UNKNOWN
Classifier: Programming Language :: Python :: 2.7
Classifier: License :: OSI Approved :: MIT License
Classifier: Operating System :: OS Independent
